{
  "main": {
    "id": "40fe9964d6bb8f08",
    "type": "split",
    "children": [
      {
        "id": "4afd4d1c6ccc6a9a",
        "type": "tabs",
        "children": [
          {
            "id": "f248a313db3089d6",
            "type": "leaf",
            "state": {
              "type": "markdown",
              "state": {
                "file": "2-무대/교통-통신.md",
                "mode": "source",
                "source": false
              },
              "icon": "lucide-file",
              "title": "교통-통신"
            }
          }
        ]
      }
    ],
    "direction": "vertical"
  },
  "left": {
    "id": "8e9d495f90c9c144",
    "type": "split",
    "children": [
      {
        "id": "603d923950e5175f",
        "type": "tabs",
        "children": [
          {
            "id": "c30c3a9df6165fa9",
            "type": "leaf",
            "state": {
              "type": "file-explorer",
              "state": {
                "sortOrder": "alphabetical",
                "autoReveal": false
              },
              "icon": "lucide-folder-closed",
              "title": "파일 탐색기"
            }
          },
          {
            "id": "8e0fe9d023b1bf9d",
            "type": "leaf",
            "state": {
              "type": "search",
              "state": {
                "query": "",
                "matchingCase": false,
                "explainSearch": false,
                "collapseAll": false,
                "extraContext": false,
                "sortOrder": "alphabetical"
              },
              "icon": "lucide-search",
              "title": "검색"
            }
          },
          {
            "id": "682dfda508a829d8",
            "type": "leaf",
            "state": {
              "type": "bookmarks",
              "state": {},
              "icon": "lucide-bookmark",
              "title": "북마크"
            }
          }
        ]
      }
    ],
    "direction": "horizontal",
    "width": 766.5
  },
  "right": {
    "id": "52dab7032cf87708",
    "type": "split",
    "children": [
      {
        "id": "4bbbd7d2fb83b0ff",
        "type": "tabs",
        "children": [
          {
            "id": "ea889e69f564aba6",
            "type": "leaf",
            "state": {
              "type": "backlink",
              "state": {
                "file": "2-무대/세력/철의금융/무혈의징수단/경제상업.md",
                "collapseAll": false,
                "extraContext": false,
                "sortOrder": "alphabetical",
                "showSearch": false,
                "searchQuery": "",
                "backlinkCollapsed": false,
                "unlinkedCollapsed": true
              },
              "icon": "links-coming-in",
              "title": "경제상업 의 백링크"
            }
          },
          {
            "id": "15ab80e2a32c27c4",
            "type": "leaf",
            "state": {
              "type": "outgoing-link",
              "state": {
                "file": "2-무대/세력/철의금융/무혈의징수단/경제상업.md",
                "linksCollapsed": false,
                "unlinkedCollapsed": true
              },
              "icon": "links-going-out",
              "title": "경제상업 의 나가는 링크"
            }
          },
          {
            "id": "76e3392f7d94e378",
            "type": "leaf",
            "state": {
              "type": "tag",
              "state": {
                "sortOrder": "frequency",
                "useHierarchy": true,
                "showSearch": false,
                "searchQuery": ""
              },
              "icon": "lucide-tags",
              "title": "태그"
            }
          },
          {
            "id": "8acff9ac5ff779d5",
            "type": "leaf",
            "state": {
              "type": "all-properties",
              "state": {
                "sortOrder": "frequency",
                "showSearch": false,
                "searchQuery": ""
              },
              "icon": "lucide-archive",
              "title": "모든 속성"
            }
          },
          {
            "id": "ad9475fe9281bbd7",
            "type": "leaf",
            "state": {
              "type": "outline",
              "state": {
                "file": "2-무대/세력/철의금융/무혈의징수단/경제상업.md",
                "followCursor": false,
                "showSearch": false,
                "searchQuery": ""
              },
              "icon": "lucide-list",
              "title": "경제상업 의 개요"
            }
          }
        ]
      }
    ],
    "direction": "horizontal",
    "width": 300,
    "collapsed": true
  },
  "left-ribbon": {
    "hiddenItems": {
      "switcher:빠른 전환기 열기": false,
      "graph:그래프 뷰 열기": false,
      "canvas:새 캔버스 만들기": false,
      "daily-notes:오늘의 일일 노트 열기": false,
      "templates:템플릿 삽입": false,
      "command-palette:명령어 팔레트 열기": false,
      "bases:새 베이스 생성하기": false
    }
  },
  "active": "f248a313db3089d6",
  "lastOpenFiles": [
    "4-인물/인물-백과/주인공일행/팻/페르디타Perdita.md",
    "4-인물/인물-백과/조역단역/낯선사내.md",
    "4-인물/인물-백과/조역단역/이름없는소환사.md",
    "4-인물/인물-백과/조역단역/베로니카.md",
    "4-인물/인물-백과/조역단역/가르나크.md",
    "4-인물/인물-백과/조역단역/마르코블랙잭.md",
    "1-시스템/소환체계.md.tmp.45892.e2e3302cded3",
    "_개명-후보안-2026-07-15.md",
    "4-인물/인물-백과/조역단역/향신료노파.md",
    "4-인물/인물-백과/조역단역/지도파는사내.md",
    "4-인물/인물-백과/조역단역/지도파는사내.md.tmp.47136.76bfe3fda003",
    "4-인물/인물-백과/조역단역/정보상노인.md",
    "2-무대/세력/_세력-비교-원장.md",
    "4-인물/인물-백과/조역단역/신성계약단지휘관.md",
    "4-인물/인물-백과/조역단역/신성계약단지휘관.md.tmp.47136.61258c09ac0b",
    "0-헌법/연대기/크로니클3-천극-앵커시드.md.tmp.47136.27b779ea5598",
    "4-인물/인물-백과/조역단역/수수께끼의세남자.md",
    "2-무대/에테르대륙/마나코어-계쟁전장.md",
    "4-인물/인물-백과/조역단역/index.md",
    "4-인물/인물-백과/조역단역",
    "2-무대/에테르대륙/지하-대균열.md",
    "4-인물/_소환체딱지_매핑대장.md",
    "_품질감사-10렌즈-2026-07-15.md",
    "3-사물/세트-장비/이시스-아스트라-계보-세트.md",
    "3-사물/아이템-도감/01-19-1.무기/01.한손검/녹슨 톱날검 (Rusty Sawblade).md",
    "3-사물/아이템-도감/01-19-1.무기/01.한손검/네메시안 (Nemesian).md",
    "3-사물/아이템-도감/01-19-1.무기/01.한손검/나이트스트라이크의 명령 (Nightstrike's Command).md",
    "3-사물/아이템-도감/01-19-1.무기/01.한손검/그로브송 (Grovesong).md",
    "3-사물/아이템-도감/01-19-1.무기/01.한손검/경야검 이시스-아스트라 (Wake Blade Isis-Astra).md",
    "3-사물/아이템-도감/01-19-1.무기/01.한손검/고행검 이시스-아스트라 (Penitent Blade Isis-Astra).md",
    "2-무대/지도/_이미지-생성-프롬프트.md",
    "2-무대/지도/베르나-시가.svg",
    "2-무대/지도/에테르전도.svg",
    "2-무대/지도/세계전도.svg",
    "2-무대/지도",
    "2-무대/세력/그림자첩보/어둠의손/어둠의손.md.tmp.2928.4c2b25b84c15",
    "0-헌법/연대기/Act1-1A-1장-화별콘티.md.tmp.63924.5452275d8507",
    "4-인물/인물-백과/주요인물/해양대륙",
    "4-인물/인물-백과/주요인물/오벨리스크대륙"
  ]
}