{
  "main": {
    "id": "40fe9964d6bb8f08",
    "type": "split",
    "children": [
      {
        "id": "4afd4d1c6ccc6a9a",
        "type": "tabs",
        "children": [
          {
            "id": "f248a313db3089d6",
            "type": "leaf",
            "state": {
              "type": "markdown",
              "state": {
                "file": "4-인물/영웅-백과/01-14-3.소환영웅/2.전설급/01.알렉시온볼트리안.md",
                "mode": "source",
                "source": false
              },
              "icon": "lucide-file",
              "title": "01.알렉시온볼트리안"
            }
          }
        ]
      }
    ],
    "direction": "vertical"
  },
  "left": {
    "id": "8e9d495f90c9c144",
    "type": "split",
    "children": [
      {
        "id": "603d923950e5175f",
        "type": "tabs",
        "children": [
          {
            "id": "c30c3a9df6165fa9",
            "type": "leaf",
            "state": {
              "type": "file-explorer",
              "state": {
                "sortOrder": "alphabetical",
                "autoReveal": false
              },
              "icon": "lucide-folder-closed",
              "title": "파일 탐색기"
            }
          },
          {
            "id": "8e0fe9d023b1bf9d",
            "type": "leaf",
            "state": {
              "type": "search",
              "state": {
                "query": "",
                "matchingCase": false,
                "explainSearch": false,
                "collapseAll": false,
                "extraContext": false,
                "sortOrder": "alphabetical"
              },
              "icon": "lucide-search",
              "title": "검색"
            }
          },
          {
            "id": "682dfda508a829d8",
            "type": "leaf",
            "state": {
              "type": "bookmarks",
              "state": {},
              "icon": "lucide-bookmark",
              "title": "북마크"
            }
          }
        ]
      }
    ],
    "direction": "horizontal",
    "width": 300
  },
  "right": {
    "id": "52dab7032cf87708",
    "type": "split",
    "children": [
      {
        "id": "4bbbd7d2fb83b0ff",
        "type": "tabs",
        "children": [
          {
            "id": "ea889e69f564aba6",
            "type": "leaf",
            "state": {
              "type": "backlink",
              "state": {
                "file": "4-인물/영웅-백과/01-14-3.소환영웅/2.전설급/01.알렉시온볼트리안.md",
                "collapseAll": false,
                "extraContext": false,
                "sortOrder": "alphabetical",
                "showSearch": false,
                "searchQuery": "",
                "backlinkCollapsed": false,
                "unlinkedCollapsed": true
              },
              "icon": "links-coming-in",
              "title": "01.알렉시온볼트리안 의 백링크"
            }
          },
          {
            "id": "15ab80e2a32c27c4",
            "type": "leaf",
            "state": {
              "type": "outgoing-link",
              "state": {
                "file": "4-인물/영웅-백과/01-14-3.소환영웅/2.전설급/01.알렉시온볼트리안.md",
                "linksCollapsed": false,
                "unlinkedCollapsed": true
              },
              "icon": "links-going-out",
              "title": "01.알렉시온볼트리안 의 나가는 링크"
            }
          },
          {
            "id": "76e3392f7d94e378",
            "type": "leaf",
            "state": {
              "type": "tag",
              "state": {
                "sortOrder": "frequency",
                "useHierarchy": true,
                "showSearch": false,
                "searchQuery": ""
              },
              "icon": "lucide-tags",
              "title": "태그"
            }
          },
          {
            "id": "8acff9ac5ff779d5",
            "type": "leaf",
            "state": {
              "type": "all-properties",
              "state": {
                "sortOrder": "frequency",
                "showSearch": false,
                "searchQuery": ""
              },
              "icon": "lucide-archive",
              "title": "모든 속성"
            }
          },
          {
            "id": "ad9475fe9281bbd7",
            "type": "leaf",
            "state": {
              "type": "outline",
              "state": {
                "file": "4-인물/영웅-백과/01-14-3.소환영웅/2.전설급/01.알렉시온볼트리안.md",
                "followCursor": false,
                "showSearch": false,
                "searchQuery": ""
              },
              "icon": "lucide-list",
              "title": "01.알렉시온볼트리안 의 개요"
            }
          }
        ]
      }
    ],
    "direction": "horizontal",
    "width": 300,
    "collapsed": true
  },
  "left-ribbon": {
    "hiddenItems": {
      "switcher:빠른 전환기 열기": false,
      "graph:그래프 뷰 열기": false,
      "canvas:새 캔버스 만들기": false,
      "daily-notes:오늘의 일일 노트 열기": false,
      "templates:템플릿 삽입": false,
      "command-palette:명령어 팔레트 열기": false,
      "bases:새 베이스 생성하기": false
    }
  },
  "active": "f248a313db3089d6",
  "lastOpenFiles": [
    "4-인물/영웅-백과/01-14-1.성장영웅/7.무소속및방랑자/칼도르빈.md.tmp.55816.65c2056bbac1",
    "4-인물/영웅-백과/01-14-1.성장영웅/7.무소속및방랑자/칼도르빈.md.tmp.55816.18a260a43341",
    "4-인물/영웅-백과/01-14-1.성장영웅/7.무소속및방랑자/이셀라렌.md.tmp.55816.2d18fd2f8e9f",
    "4-인물/영웅-백과/01-14-1.성장영웅/7.무소속및방랑자/칼도르빈.md.tmp.55816.4751187c1952",
    "4-인물/영웅-백과/01-14-1.성장영웅/7.무소속및방랑자/이셀라렌.md.tmp.55816.ff4466293da6",
    "4-인물/영웅-백과/01-14-1.성장영웅/7.무소속및방랑자/칼도르빈.md.tmp.55816.7fe9a62f43e1",
    "3-사물/아이템-도감/01-19-2.방어구/01.중갑/진흙에 절여진 진혼 갑주 (Mud-Steeped Requiem Plate).md",
    "3-사물/아이템-도감/01-19-1.무기/16.특수·마도구·기타/위선의 램프 (Lamp of Hypocrisy).md.tmp.55816.1e657a8ba020",
    "3-사물/아이템-도감/01-19-1.무기/16.특수·마도구·기타/묘지기의 관 (Coffin of Weapons).md",
    "3-사물/아이템-도감/01-19-4.유물/04.영웅고유성유물/죽은 자의 장막 (Veil of the Dead).md",
    "4-인물/영웅-백과/01-14-1.성장영웅/6.범대륙초국가및중립영웅/6-7.그림자첩보조직소속/7.옴니버스서고/트리스탄아이언사이드.md.tmp.55816.eb85566cec91",
    "4-인물/영웅-백과/01-14-1.성장영웅/6.범대륙초국가및중립영웅/6-7.그림자첩보조직소속/5.황금손아귀/기네비어어스바운드.md.tmp.55816.55c30bfbee83",
    "4-인물/영웅-백과/01-14-1.성장영웅/6.범대륙초국가및중립영웅/6-7.그림자첩보조직소속/5.황금손아귀/기네비어어스바운드.md.tmp.55816.f321ec3ea0ab",
    "4-인물/영웅-백과/01-14-1.성장영웅/6.범대륙초국가및중립영웅/6-7.그림자첩보조직소속/5.황금손아귀/기네비어어스바운드.md.tmp.55816.0e6d27a08fbc",
    "3-사물/아이템-도감/01-19-4.유물/04.영웅고유성유물/빈혈의 시계태엽 심장 (Anemic Clockwork).md",
    "3-사물/아이템-도감/01-19-4.유물/04.영웅고유성유물/침묵의 마스크 (Mask of Silence).md",
    "3-사물/아이템-도감/01-19-2.방어구/07.견갑/야수화된 철극 견갑 (Beastial Pauldrons of the Feral Marrow).md",
    "3-사물/아이템-도감/01-19-3.악세서리/01.반지/기울지 않는 저울반지 (Ring of the Unbending Scale).md",
    "3-사물/아이템-도감/01-19-3.악세서리/06.훈장/가문의 낡은 은훈장 — 침묵한 긍지 (Old Silver House-Medal — Silenced Pride).md",
    "3-사물/아이템-도감/01-19-4.유물/04.영웅고유성유물/나이테의 고서 실바노멘 (Sylvanomen, Codex of the Growth-Rings).md",
    "3-사물/아이템-도감/01-19-2.방어구/04.망토·외투/여행자의 로브 — 별빛 인도자의 안식 (Traveler's Robe of the Starward Guide's Repose).md",
    "3-사물/아이템-도감/01-19-2.방어구/01.중갑/여명의 순찰갑 — 무명자의 맹세 (Dawn-Watch Plate — Vow of the Nameless).md",
    "3-사물/아이템-도감/01-19-1.무기/10.활·석궁/정령의 활 실페리시움 (Spirit Bow Sylpherisium).md",
    "3-사물/아이템-도감/01-19-1.무기/12.지팡이·완드/세계수 파편의 순례자봉 '에스더의 안식처' (Pilgrim's Bough of the World Tree Shard, Esther's Sanctuary).md",
    "3-사물/아이템-도감/01-19-1.무기/10.활·석궁/바람정찰활 시라니엘 (Sylaniel, Scoutbow of the Windward).md",
    "3-사물/아이템-도감/01-19-1.무기/01.한손검/서약검 이시스-아스트라 (Oathblade Isis-Astra).md",
    "3-사물/아이템-도감/01-19-4.유물/04.영웅고유성유물/진동의 흑요석 (Resonance Obsidian).md",
    "3-사물/아이템-도감/01-19-1.무기/01.한손검/솔라리스 렉스 (Solaris Rex).md",
    "3-사물/아이템-도감/01-19-1.무기/01.한손검/숲의 서약검 실바니우스 (Sylvanius, Oathblade of the Woodland).md",
    "3-사물/아이템-도감/01-19-1.무기/16.특수·마도구·기타/통곡의 문살 (Weeping Gate).md",
    "3-사물/아이템-도감/01-19-2.방어구/04.망토·외투/카디널 가문의 청람 제복 외투 (Cardinal House's Azure Vigil Coat).md",
    "3-사물/아이템-도감/01-19-1.무기/10.활·석궁/정령의 활 — 여우의 침묵 (Spirit Bow, the Fox's Hush).md",
    "3-사물/아이템-도감/01-19-1.무기/01.한손검/카디널 파수대의 서약검 '별빛에 지지 않는 밤' (Cardinal Vigil's Oathblade — Night That Yields to No Star).md",
    "3-사물/아이템-도감/01-19-3.악세서리/07.부적/별빛 위장 부적 — 시리우스 에스더의 이중 서약패 (Starlight Disguise Talisman — Sirius Esther's Twofold Oath Plate).md",
    "3-사물/아이템-도감/01-19-2.방어구/04.망토·외투/여행자의 로브 — 여명의 파수꾼 (Traveler's Robe of the Dawn-Watcher).md",
    "3-사물/아이템-도감/01-19-1.무기/01.한손검/별의 잔영을 벼린 이중검 — 시리우스 에스더의 야경검 (Blade of Star-Afterimage — Sirius Esther's Night-Vigil Sword).md"
  ]
}